main.py
sceptre_aws_resolver-0.4.dist-info/METADATA
sceptre_aws_resolver-0.4.dist-info/WHEEL
sceptre_aws_resolver-0.4.dist-info/entry_points.txt
sceptre_aws_resolver-0.4.dist-info/top_level.txt
sceptre_aws_resolver-0.4.dist-info/RECORD
