Metadata-Version: 2.1
Name: sceptre-aws-resolver
Version: 0.4
Summary: Sceptre AWS resolver
Home-page: https://github.com/jeshan/sceptre-aws-resolver
Author: Jeshan G. BABOOA
Author-email: j@jeshan.co
License: BSD-2-Clause
Keywords: sceptre
Platform: UNKNOWN
Classifier: Programming Language :: Python :: 3
Classifier: Programming Language :: Python :: 3.5
Classifier: License :: OSI Approved :: BSD License
Classifier: Operating System :: OS Independent
Requires-Dist: sceptre (>=2.0)
